{
  "title": "Personal Residencies",
  "subtitle": "Second residence or full relocation",
  "description": "Based on your needs and budget, I search the market for properties on your behalf, curating a list of properties for your consideration. All you have to do is view the properties you like, and when we find the perfect match, I negotiate the deal and follow through with the buying process to completion.",
  "price": "\u20ac11,000",
  "priceNote": "Fixed fee regardless of property price",
  "image": "/images/PersonalResidencies.png",
  "ctaLabel": "Get Started",
  "features": [
    "Personalized property search",
    "Neighbourhood guidance",
    "School recommendations",
    "Curated property shortlists",
    "Property viewings coordination",
    "Due diligence & legal checks",
    "Offer submission & negotiation"
  ],
  "order": 1
}
